odoo10_addon_partner_multi_relation_hierarchy-10.0.0.1.0.99.dev4-nspkg.pth
odoo/addons/partner_multi_relation_hierarchy/README.rst
odoo/addons/partner_multi_relation_hierarchy/__init__.py
odoo/addons/partner_multi_relation_hierarchy/__manifest__.py
odoo/addons/partner_multi_relation_hierarchy/i18n/nl.po
odoo/addons/partner_multi_relation_hierarchy/i18n/partner_multi_relation_hierarchy.pot
odoo/addons/partner_multi_relation_hierarchy/models/__init__.py
odoo/addons/partner_multi_relation_hierarchy/models/res_partner.py
odoo/addons/partner_multi_relation_hierarchy/models/res_partner_relation.py
odoo/addons/partner_multi_relation_hierarchy/models/res_partner_relation_hierarchy.py
odoo/addons/partner_multi_relation_hierarchy/models/res_partner_relation_type.py
odoo/addons/partner_multi_relation_hierarchy/security/ir.model.access.csv
odoo/addons/partner_multi_relation_hierarchy/static/description/icon.png
odoo/addons/partner_multi_relation_hierarchy/tests/__init__.py
odoo/addons/partner_multi_relation_hierarchy/tests/test_partner_hierarchy.py
odoo/addons/partner_multi_relation_hierarchy/views/res_partner.xml
odoo/addons/partner_multi_relation_hierarchy/views/res_partner_relation_type.xml
odoo10_addon_partner_multi_relation_hierarchy-10.0.0.1.0.99.dev4.dist-info/METADATA
odoo10_addon_partner_multi_relation_hierarchy-10.0.0.1.0.99.dev4.dist-info/WHEEL
odoo10_addon_partner_multi_relation_hierarchy-10.0.0.1.0.99.dev4.dist-info/namespace_packages.txt
odoo10_addon_partner_multi_relation_hierarchy-10.0.0.1.0.99.dev4.dist-info/top_level.txt
odoo10_addon_partner_multi_relation_hierarchy-10.0.0.1.0.99.dev4.dist-info/RECORD
