Metadata-Version: 2.1
Name: odoo10-addon-partner-multi-relation-hierarchy
Version: 10.0.0.1.0.99.dev4
Summary: Partner Relation Hierarchy
Home-page: https://github.com/oca/partner-contact
Author: Therp BV, Odoo Community Association (OCA)
Author-email: support@odoo-community.org
License: AGPL-3
Platform: UNKNOWN
Classifier: Programming Language :: Python
Classifier: Framework :: Odoo
Classifier: License :: OSI Approved :: GNU Affero General Public License v3
Requires-Python: ~=2.7
Requires-Dist: odoo10-addon-partner-multi-relation
Requires-Dist: odoo (<10.1dev,>=10.0)
